nonebot_plugin_figurine/__init__.py
nonebot_plugin_figurine/config.py
nonebot_plugin_figurine-0.2.5.dist-info/METADATA
nonebot_plugin_figurine-0.2.5.dist-info/WHEEL
nonebot_plugin_figurine-0.2.5.dist-info/licenses/LICENSE
nonebot_plugin_figurine-0.2.5.dist-info/RECORD
