Metadata-Version: 2.4
Name: nonebot-plugin-figurine
Version: 0.2.5
Summary: NoneBot2 一个图片手办化插件
License-File: LICENSE
Keywords: nonebot2,nonebot-plugin-figurine
Author: padoru233
Author-email: wr15624916906@gmail.com
Requires-Python: >=3.9
Classifier: Programming Language :: Python :: 3
Classifier: Programming Language :: Python :: 3.9
Classifier: Programming Language :: Python :: 3.10
Classifier: Programming Language :: Python :: 3.11
Classifier: Programming Language :: Python :: 3.12
Classifier: Programming Language :: Python :: 3.13
Classifier: Programming Language :: Python :: 3.14
Requires-Dist: Pillow (>=8.4.0)
Requires-Dist: httpx (>=0.27.2,<1.0.0)
Requires-Dist: nonebot-adapter-onebot (>=2.0.0,<3.0.0)
Requires-Dist: nonebot2 (>=2.2.0)
Project-URL: Homepage, https://github.com/padoru233/nonebot-plugin-figurine
Project-URL: Repository, https://github.com/padoru233/nonebot-plugin-figurine
